LICENSE
README.md
httpsdate.py
requirements.txt
setup.py
httpsdate.egg-info/PKG-INFO
httpsdate.egg-info/SOURCES.txt
httpsdate.egg-info/dependency_links.txt
httpsdate.egg-info/requires.txt
httpsdate.egg-info/top_level.txt