Metadata-Version: 2.1
Name: httpsdate
Version: 0.2.0
Summary: Simple and secure system time synchronisation over HTTPS
Home-page: https://github.com/s-hamann/httpsdate
Author: Sebastian Hamann
Author-email: code@ares-macrotechnology.com
License: MIT
Keywords: Security,Time Synchronization
Platform: Linux
Classifier: License :: OSI Approved :: MIT License
Classifier: Programming Language :: Python :: 3.4
Classifier: Programming Language :: Python :: 3.5
Classifier: Programming Language :: Python :: 3.6
Classifier: Operating System :: POSIX :: Linux
Classifier: Topic :: Security
Classifier: Topic :: System :: Networking :: Time Synchronization
Requires-Python: >=3.4.3
